{
"meta":{"test_sets":[],"test_metrics":[],"learn_metrics":[{"best_value":"Min","name":"RMSE"}],"launch_mode":"Train","parameters":"","iteration_count":100,"learn_sets":["learn"],"name":"experiment"},
"iterations":[
{"learn":[0.3757098389],"iteration":0,"passed_time":0.05075632822,"remaining_time":5.024876494},
{"learn":[0.3468771685],"iteration":1,"passed_time":0.05788039171,"remaining_time":2.836139194},
{"learn":[0.3343405169],"iteration":2,"passed_time":0.06152021707,"remaining_time":1.989153685},
{"learn":[0.3258143605],"iteration":3,"passed_time":0.06496633712,"remaining_time":1.559192091},
{"learn":[0.3218853272],"iteration":4,"passed_time":0.06794652261,"remaining_time":1.29098393},
{"learn":[0.3194044434],"iteration":5,"passed_time":0.07210183052,"remaining_time":1.129595345},
{"learn":[0.316500884],"iteration":6,"passed_time":0.07560910347,"remaining_time":1.004520946},
{"learn":[0.3147380319],"iteration":7,"passed_time":0.07977059468,"remaining_time":0.9173618388},
{"learn":[0.313564032],"iteration":8,"passed_time":0.08392771035,"remaining_time":0.8486024047},
{"learn":[0.3129503049],"iteration":9,"passed_time":0.08742519726,"remaining_time":0.7868267754},
{"learn":[0.3112726806],"iteration":10,"passed_time":0.09065137716,"remaining_time":0.7334520516},
{"learn":[0.3101553094],"iteration":11,"passed_time":0.09371603984,"remaining_time":0.6872509589},
{"learn":[0.3091466911],"iteration":12,"passed_time":0.09701742089,"remaining_time":0.6492704321},
{"learn":[0.3082521398],"iteration":13,"passed_time":0.1001525636,"remaining_time":0.6152228909},
{"learn":[0.3077015265],"iteration":14,"passed_time":0.1032760154,"remaining_time":0.5852307537},
{"learn":[0.3071978887],"iteration":15,"passed_time":0.1064474779,"remaining_time":0.5588492587},
{"learn":[0.3065470222],"iteration":16,"passed_time":0.1097568877,"remaining_time":0.5358718636},
{"learn":[0.3056751887],"iteration":17,"passed_time":0.1131749519,"remaining_time":0.5155747807},
{"learn":[0.3053966595],"iteration":18,"passed_time":0.116200047,"remaining_time":0.4953791479},
{"learn":[0.3043081574],"iteration":19,"passed_time":0.119274593,"remaining_time":0.4770983719},
{"learn":[0.3037013436],"iteration":20,"passed_time":0.1227478917,"remaining_time":0.4617658784},
{"learn":[0.3032918665],"iteration":21,"passed_time":0.1259540123,"remaining_time":0.4465642255},
{"learn":[0.3029288083],"iteration":22,"passed_time":0.1291820517,"remaining_time":0.4324790425},
{"learn":[0.3023833575],"iteration":23,"passed_time":0.1323169344,"remaining_time":0.4190036256},
{"learn":[0.3014764989],"iteration":24,"passed_time":0.1352902111,"remaining_time":0.4058706332},
{"learn":[0.300981173],"iteration":25,"passed_time":0.1385425308,"remaining_time":0.3943133568},
{"learn":[0.3006907063],"iteration":26,"passed_time":0.1417638285,"remaining_time":0.3832873881},
{"learn":[0.300162242],"iteration":27,"passed_time":0.1449967378,"remaining_time":0.3728487543},
{"learn":[0.298553433],"iteration":28,"passed_time":0.148539186,"remaining_time":0.3636649037},
{"learn":[0.2982094895],"iteration":29,"passed_time":0.1519068722,"remaining_time":0.3544493684},
{"learn":[0.2974754029],"iteration":30,"passed_time":0.1557339707,"remaining_time":0.3466336767},
{"learn":[0.2964980386],"iteration":31,"passed_time":0.1591501259,"remaining_time":0.3381940176},
{"learn":[0.2961460932],"iteration":32,"passed_time":0.1630662405,"remaining_time":0.3310738823},
{"learn":[0.2956424648],"iteration":33,"passed_time":0.1686608885,"remaining_time":0.3274005482},
{"learn":[0.2950986817],"iteration":34,"passed_time":0.1750629831,"remaining_time":0.3251169685},
{"learn":[0.2946217143],"iteration":35,"passed_time":0.1789421357,"remaining_time":0.3181193523},
{"learn":[0.2939878315],"iteration":36,"passed_time":0.1826031825,"remaining_time":0.3109189324},
{"learn":[0.2934717786],"iteration":37,"passed_time":0.186162284,"remaining_time":0.3037384634},
{"learn":[0.2925854484],"iteration":38,"passed_time":0.1899744021,"remaining_time":0.2971394494},
{"learn":[0.2922247769],"iteration":39,"passed_time":0.1968138975,"remaining_time":0.2952208463},
{"learn":[0.2919782249],"iteration":40,"passed_time":0.2003363982,"remaining_time":0.2882889632},
{"learn":[0.2916576363],"iteration":41,"passed_time":0.2048079289,"remaining_time":0.282829997},
{"learn":[0.2911749591],"iteration":42,"passed_time":0.2084534948,"remaining_time":0.2763220745},
{"learn":[0.2906550136],"iteration":43,"passed_time":0.2122373597,"remaining_time":0.270120276},
{"learn":[0.2902261471],"iteration":44,"passed_time":0.2175762078,"remaining_time":0.2659264762},
{"learn":[0.2896855075],"iteration":45,"passed_time":0.2208583645,"remaining_time":0.2592685148},
{"learn":[0.2892457411],"iteration":46,"passed_time":0.2296608703,"remaining_time":0.2589792792},
{"learn":[0.2886269509],"iteration":47,"passed_time":0.2332944457,"remaining_time":0.2527356495},
{"learn":[0.2872180069],"iteration":48,"passed_time":0.2377064929,"remaining_time":0.2474087987},
{"learn":[0.2869697494],"iteration":49,"passed_time":0.2413129735,"remaining_time":0.2413129735},
{"learn":[0.2861506979],"iteration":50,"passed_time":0.246991252,"remaining_time":0.2373053205},
{"learn":[0.2858144],"iteration":51,"passed_time":0.250705403,"remaining_time":0.231420372},
{"learn":[0.2852459246],"iteration":52,"passed_time":0.2551743487,"remaining_time":0.2262866866},
{"learn":[0.2844541151],"iteration":53,"passed_time":0.2590658229,"remaining_time":0.220685701},
{"learn":[0.2839748796],"iteration":54,"passed_time":0.2638300616,"remaining_time":0.2158609595},
{"learn":[0.2835361463],"iteration":55,"passed_time":0.2688951877,"remaining_time":0.2112747903},
{"learn":[0.2832346394],"iteration":56,"passed_time":0.2729308986,"remaining_time":0.2058952393},
{"learn":[0.2828285619],"iteration":57,"passed_time":0.2771322951,"remaining_time":0.2006820068},
{"learn":[0.2822843604],"iteration":58,"passed_time":0.2804111296,"remaining_time":0.1948619714},
{"learn":[0.2816902705],"iteration":59,"passed_time":0.2873339339,"remaining_time":0.191555956},
{"learn":[0.2813348295],"iteration":60,"passed_time":0.2908625345,"remaining_time":0.1859612926},
{"learn":[0.2809741673],"iteration":61,"passed_time":0.2942858836,"remaining_time":0.1803687674},
{"learn":[0.2806908325],"iteration":62,"passed_time":0.2973702101,"remaining_time":0.1746459964},
{"learn":[0.280053482],"iteration":63,"passed_time":0.3019449273,"remaining_time":0.1698440216},
{"learn":[0.2796633663],"iteration":64,"passed_time":0.3062169227,"remaining_time":0.1648860353},
{"learn":[0.2792925716],"iteration":65,"passed_time":0.3093105369,"remaining_time":0.1593417917},
{"learn":[0.2786823039],"iteration":66,"passed_time":0.3129518756,"remaining_time":0.154140476},
{"learn":[0.2785996019],"iteration":67,"passed_time":0.3167417432,"remaining_time":0.149054938},
{"learn":[0.2780882148],"iteration":68,"passed_time":0.3213790861,"remaining_time":0.1443877054},
{"learn":[0.2777091093],"iteration":69,"passed_time":0.3253916628,"remaining_time":0.1394535698},
{"learn":[0.2772007108],"iteration":70,"passed_time":0.3288793398,"remaining_time":0.1343309979},
{"learn":[0.2769795548],"iteration":71,"passed_time":0.3325445633,"remaining_time":0.1293228857},
{"learn":[0.2766438583],"iteration":72,"passed_time":0.3361755076,"remaining_time":0.1243388864},
{"learn":[0.27641334],"iteration":73,"passed_time":0.3400335465,"remaining_time":0.1194712461},
{"learn":[0.2762552283],"iteration":74,"passed_time":0.3429251176,"remaining_time":0.1143083725},
{"learn":[0.2759677469],"iteration":75,"passed_time":0.3467650799,"remaining_time":0.1095047621},
{"learn":[0.2755948361],"iteration":76,"passed_time":0.3538455759,"remaining_time":0.1056941331},
{"learn":[0.2753451419],"iteration":77,"passed_time":0.3575179088,"remaining_time":0.1008383845},
{"learn":[0.2749496572],"iteration":78,"passed_time":0.362031311,"remaining_time":0.09623617127},
{"learn":[0.2742756813],"iteration":79,"passed_time":0.3672086368,"remaining_time":0.0918021592},
{"learn":[0.2739280397],"iteration":80,"passed_time":0.370753235,"remaining_time":0.08696680822},
{"learn":[0.2733153868],"iteration":81,"passed_time":0.3744499211,"remaining_time":0.08219632415},
{"learn":[0.2729336811],"iteration":82,"passed_time":0.3824577207,"remaining_time":0.07833471388},
{"learn":[0.2727956893],"iteration":83,"passed_time":0.3915772982,"remaining_time":0.07458615203},
{"learn":[0.2723245808],"iteration":84,"passed_time":0.4161197895,"remaining_time":0.07343290402},
{"learn":[0.2718377148],"iteration":85,"passed_time":0.4205165079,"remaining_time":0.06845617571},
{"learn":[0.2714779447],"iteration":86,"passed_time":0.4237359229,"remaining_time":0.06331686204},
{"learn":[0.271076885],"iteration":87,"passed_time":0.4304979211,"remaining_time":0.05870426196},
{"learn":[0.2707457388],"iteration":88,"passed_time":0.4338178787,"remaining_time":0.05361794006},
{"learn":[0.2705655621],"iteration":89,"passed_time":0.4373596875,"remaining_time":0.04859552083},
{"learn":[0.2703085867],"iteration":90,"passed_time":0.4436628411,"remaining_time":0.04387874252},
{"learn":[0.2701122461],"iteration":91,"passed_time":0.4484885216,"remaining_time":0.03899900188},
{"learn":[0.2696789003],"iteration":92,"passed_time":0.454739905,"remaining_time":0.03422773478},
{"learn":[0.2692007812],"iteration":93,"passed_time":0.4594722189,"remaining_time":0.02932801397},
{"learn":[0.2689064005],"iteration":94,"passed_time":0.4627113398,"remaining_time":0.02435322841},
{"learn":[0.2685954055],"iteration":95,"passed_time":0.4658520959,"remaining_time":0.01941050399},
{"learn":[0.2682461393],"iteration":96,"passed_time":0.4698469466,"remaining_time":0.01453134886},
{"learn":[0.268010368],"iteration":97,"passed_time":0.4735815924,"remaining_time":0.009664930457},
{"learn":[0.2675729341],"iteration":98,"passed_time":0.4784024096,"remaining_time":0.004832347572},
{"learn":[0.2669777503],"iteration":99,"passed_time":0.4823363596,"remaining_time":0}
]}