{
"meta":{"test_sets":[],"test_metrics":[],"learn_metrics":[{"best_value":"Min","name":"RMSE"}],"launch_mode":"Train","parameters":"","iteration_count":100,"learn_sets":["learn"],"name":"experiment"},
"iterations":[
{"learn":[0.3757098389],"iteration":0,"passed_time":0.05626580932,"remaining_time":5.570315123},
{"learn":[0.3468771685],"iteration":1,"passed_time":0.05983201929,"remaining_time":2.931768945},
{"learn":[0.3343405169],"iteration":2,"passed_time":0.06353844265,"remaining_time":2.054409646},
{"learn":[0.3258143605],"iteration":3,"passed_time":0.06815331067,"remaining_time":1.635679456},
{"learn":[0.3218853272],"iteration":4,"passed_time":0.07251852243,"remaining_time":1.377851926},
{"learn":[0.3194044434],"iteration":5,"passed_time":0.07625430441,"remaining_time":1.194650769},
{"learn":[0.316500884],"iteration":6,"passed_time":0.08010460759,"remaining_time":1.064246929},
{"learn":[0.3147380319],"iteration":7,"passed_time":0.08568987012,"remaining_time":0.9854335064},
{"learn":[0.313564032],"iteration":8,"passed_time":0.09124258917,"remaining_time":0.9225639572},
{"learn":[0.3129503049],"iteration":9,"passed_time":0.09490460386,"remaining_time":0.8541414347},
{"learn":[0.3112726806],"iteration":10,"passed_time":0.09862593843,"remaining_time":0.7979735018},
{"learn":[0.3101553094],"iteration":11,"passed_time":0.1030691477,"remaining_time":0.7558404162},
{"learn":[0.3091466911],"iteration":12,"passed_time":0.1068863075,"remaining_time":0.7153160579},
{"learn":[0.3082521398],"iteration":13,"passed_time":0.1106597219,"remaining_time":0.6797668628},
{"learn":[0.3077015265],"iteration":14,"passed_time":0.1154433637,"remaining_time":0.6541790611},
{"learn":[0.3071978887],"iteration":15,"passed_time":0.1190184107,"remaining_time":0.6248466559},
{"learn":[0.3065470222],"iteration":16,"passed_time":0.1247275396,"remaining_time":0.6089638697},
{"learn":[0.3056751887],"iteration":17,"passed_time":0.1286781398,"remaining_time":0.5862004148},
{"learn":[0.3053966595],"iteration":18,"passed_time":0.1325352354,"remaining_time":0.5650186353},
{"learn":[0.3043081574],"iteration":19,"passed_time":0.1361812719,"remaining_time":0.5447250877},
{"learn":[0.3037013436],"iteration":20,"passed_time":0.1397799015,"remaining_time":0.5258386771},
{"learn":[0.3032918665],"iteration":21,"passed_time":0.1452920194,"remaining_time":0.5151262506},
{"learn":[0.3029288083],"iteration":22,"passed_time":0.1495079109,"remaining_time":0.5005264842},
{"learn":[0.3023833575],"iteration":23,"passed_time":0.1537019726,"remaining_time":0.4867229133},
{"learn":[0.3014764989],"iteration":24,"passed_time":0.1573956987,"remaining_time":0.4721870962},
{"learn":[0.300981173],"iteration":25,"passed_time":0.1610476317,"remaining_time":0.4583663365},
{"learn":[0.3006907063],"iteration":26,"passed_time":0.1645984867,"remaining_time":0.4450255381},
{"learn":[0.300162242],"iteration":27,"passed_time":0.1682357201,"remaining_time":0.4326061374},
{"learn":[0.298553433],"iteration":28,"passed_time":0.1766786034,"remaining_time":0.43255796},
{"learn":[0.2982094895],"iteration":29,"passed_time":0.1800289064,"remaining_time":0.4200674483},
{"learn":[0.2974754029],"iteration":30,"passed_time":0.185745096,"remaining_time":0.4134326331},
{"learn":[0.2964980386],"iteration":31,"passed_time":0.1885607665,"remaining_time":0.4006916287},
{"learn":[0.2961460932],"iteration":32,"passed_time":0.1913095253,"remaining_time":0.388416309},
{"learn":[0.2956424648],"iteration":33,"passed_time":0.1950371435,"remaining_time":0.3786015139},
{"learn":[0.2950986817],"iteration":34,"passed_time":0.1980140922,"remaining_time":0.3677404569},
{"learn":[0.2946217143],"iteration":35,"passed_time":0.2011931691,"remaining_time":0.3576767451},
{"learn":[0.2939878315],"iteration":36,"passed_time":0.2043615184,"remaining_time":0.3479669097},
{"learn":[0.2934717786],"iteration":37,"passed_time":0.2074032241,"remaining_time":0.3383947341},
{"learn":[0.2925854484],"iteration":38,"passed_time":0.2127209548,"remaining_time":0.3327173909},
{"learn":[0.2922247769],"iteration":39,"passed_time":0.2154181182,"remaining_time":0.3231271774},
{"learn":[0.2919782249],"iteration":40,"passed_time":0.2180584374,"remaining_time":0.3137914099},
{"learn":[0.2916576363],"iteration":41,"passed_time":0.2206617834,"remaining_time":0.3047234152},
{"learn":[0.2911749591],"iteration":42,"passed_time":0.2232558953,"remaining_time":0.2959438613},
{"learn":[0.2906550136],"iteration":43,"passed_time":0.2260386224,"remaining_time":0.2876855194},
{"learn":[0.2902261471],"iteration":44,"passed_time":0.2289164015,"remaining_time":0.2797867129},
{"learn":[0.2896855075],"iteration":45,"passed_time":0.2323020985,"remaining_time":0.2727024635},
{"learn":[0.2892457411],"iteration":46,"passed_time":0.236794502,"remaining_time":0.2670235874},
{"learn":[0.2886269509],"iteration":47,"passed_time":0.2398004105,"remaining_time":0.2597837781},
{"learn":[0.2872180069],"iteration":48,"passed_time":0.2429587914,"remaining_time":0.2528754768},
{"learn":[0.2869697494],"iteration":49,"passed_time":0.2457450233,"remaining_time":0.2457450233},
{"learn":[0.2861506979],"iteration":50,"passed_time":0.2485092637,"remaining_time":0.2387638024},
{"learn":[0.2858144],"iteration":51,"passed_time":0.2512382919,"remaining_time":0.2319122694},
{"learn":[0.2852459246],"iteration":52,"passed_time":0.2540089488,"remaining_time":0.2252532187},
{"learn":[0.2844541151],"iteration":53,"passed_time":0.2574771667,"remaining_time":0.2193324013},
{"learn":[0.2839748796],"iteration":54,"passed_time":0.2603710724,"remaining_time":0.2130308774},
{"learn":[0.2835361463],"iteration":55,"passed_time":0.2644540188,"remaining_time":0.2077853005},
{"learn":[0.2832346394],"iteration":56,"passed_time":0.2673190941,"remaining_time":0.2016617727},
{"learn":[0.2828285619],"iteration":57,"passed_time":0.2714293041,"remaining_time":0.1965522547},
{"learn":[0.2822843604],"iteration":58,"passed_time":0.2748290252,"remaining_time":0.1909828819},
{"learn":[0.2816902705],"iteration":59,"passed_time":0.2781328395,"remaining_time":0.185421893},
{"learn":[0.2813348295],"iteration":60,"passed_time":0.2810169061,"remaining_time":0.1796665466},
{"learn":[0.2809741673],"iteration":61,"passed_time":0.283931324,"remaining_time":0.1740224244},
{"learn":[0.2806908325],"iteration":62,"passed_time":0.2865712793,"remaining_time":0.1683037672},
{"learn":[0.280053482],"iteration":63,"passed_time":0.2895525176,"remaining_time":0.1628732911},
{"learn":[0.2796633663],"iteration":64,"passed_time":0.2936312911,"remaining_time":0.1581091567},
{"learn":[0.2792925716],"iteration":65,"passed_time":0.2971182705,"remaining_time":0.1530609272},
{"learn":[0.2786823039],"iteration":66,"passed_time":0.3002846152,"remaining_time":0.1479013776},
{"learn":[0.2785996019],"iteration":67,"passed_time":0.3028664759,"remaining_time":0.1425254004},
{"learn":[0.2780882148],"iteration":68,"passed_time":0.3057446578,"remaining_time":0.1373635419},
{"learn":[0.2777091093],"iteration":69,"passed_time":0.3086951983,"remaining_time":0.1322979421},
{"learn":[0.2772007108],"iteration":70,"passed_time":0.3111559076,"remaining_time":0.1270918496},
{"learn":[0.2769795548],"iteration":71,"passed_time":0.313743276,"remaining_time":0.122011274},
{"learn":[0.2766438583],"iteration":72,"passed_time":0.3165839187,"remaining_time":0.1170926823},
{"learn":[0.27641334],"iteration":73,"passed_time":0.3194320299,"remaining_time":0.1122328754},
{"learn":[0.2762552283],"iteration":74,"passed_time":0.3235552559,"remaining_time":0.107851752},
{"learn":[0.2759677469],"iteration":75,"passed_time":0.3263111482,"remaining_time":0.1030456258},
{"learn":[0.2755948361],"iteration":76,"passed_time":0.3290324775,"remaining_time":0.09828242835},
{"learn":[0.2753451419],"iteration":77,"passed_time":0.3323411007,"remaining_time":0.09373723354},
{"learn":[0.2749496572],"iteration":78,"passed_time":0.3355507855,"remaining_time":0.08919704424},
{"learn":[0.2742756813],"iteration":79,"passed_time":0.3386191643,"remaining_time":0.08465479106},
{"learn":[0.2739280397],"iteration":80,"passed_time":0.3416272762,"remaining_time":0.08013479317},
{"learn":[0.2733153868],"iteration":81,"passed_time":0.3485761555,"remaining_time":0.07651671705},
{"learn":[0.2729336811],"iteration":82,"passed_time":0.3516986791,"remaining_time":0.07203466922},
{"learn":[0.2727956893],"iteration":83,"passed_time":0.3557905748,"remaining_time":0.06776963329},
{"learn":[0.2723245808],"iteration":84,"passed_time":0.3598857486,"remaining_time":0.06350924975},
{"learn":[0.2718377148],"iteration":85,"passed_time":0.3627270573,"remaining_time":0.05904859073},
{"learn":[0.2714779447],"iteration":86,"passed_time":0.3655133714,"remaining_time":0.05461694055},
{"learn":[0.271076885],"iteration":87,"passed_time":0.3687817306,"remaining_time":0.0502884178},
{"learn":[0.2707457388],"iteration":88,"passed_time":0.3718535864,"remaining_time":0.04595943202},
{"learn":[0.2705655621],"iteration":89,"passed_time":0.3748144874,"remaining_time":0.04164605416},
{"learn":[0.2703085867],"iteration":90,"passed_time":0.3775688962,"remaining_time":0.03734197874},
{"learn":[0.2701122461],"iteration":91,"passed_time":0.3803944261,"remaining_time":0.03307777618},
{"learn":[0.2696789003],"iteration":92,"passed_time":0.3839001165,"remaining_time":0.02889570769},
{"learn":[0.2692007812],"iteration":93,"passed_time":0.3870700371,"remaining_time":0.02470659811},
{"learn":[0.2689064005],"iteration":94,"passed_time":0.390116209,"remaining_time":0.02053243205},
{"learn":[0.2685954055],"iteration":95,"passed_time":0.3947974071,"remaining_time":0.01644989196},
{"learn":[0.2682461393],"iteration":96,"passed_time":0.3978654043,"remaining_time":0.0123051156},
{"learn":[0.268010368],"iteration":97,"passed_time":0.4015758495,"remaining_time":0.008195425501},
{"learn":[0.2675729341],"iteration":98,"passed_time":0.4048068702,"remaining_time":0.004088958285},
{"learn":[0.2669777503],"iteration":99,"passed_time":0.4074290649,"remaining_time":0}
]}